omnimark/__init__.py
omnimark/__main__.py
omnimark/main.py
omnimark/processors/pdf_page_processor.py
omnimark/utils/__init__.py
omnimark/utils/config.py
omnimark/utils/markdown_converter.py
omnimark/utils/pdf_utils.py
omnimark/utils/table_detector.py
omnimark/utils/utils.py
omnimark-0.1.2.dist-info/LICENSE
omnimark-0.1.2.dist-info/METADATA
omnimark-0.1.2.dist-info/WHEEL
omnimark-0.1.2.dist-info/entry_points.txt
omnimark-0.1.2.dist-info/top_level.txt
omnimark-0.1.2.dist-info/RECORD
