Metadata-Version: 2.1
Name: omnimark
Version: 0.1.2
Summary: A PDF to Markdown converter with support for native, scanned, and hybrid PDFs
Home-page: https://github.com/royabes/omnimark
Author: Roy Abes
Author-email: Roy Abes <roy.abes@gmail.com>
License: MIT License
Project-URL: Homepage, https://github.com/royabes/omnimark
Project-URL: Bug Tracker, https://github.com/royabes/omnimark/issues
Keywords: pdf,markdown,converter,ocr
Classifier: Development Status :: 3 - Alpha
Classifier: Intended Audience :: Developers
Classifier: License :: OSI Approved :: MIT License
Classifier: Operating System :: OS Independent
Classifier: Programming Language :: Python :: 3
Classifier: Programming Language :: Python :: 3.7
Classifier: Programming Language :: Python :: 3.8
Classifier: Programming Language :: Python :: 3.9
Classifier: Programming Language :: Python :: 3.10
Classifier: Programming Language :: Python :: 3.11
Requires-Python: >=3.7
License-File: LICENSE
Requires-Dist: pytesseract>=0.3.0
Requires-Dist: Pillow>=8.0.0
Requires-Dist: PyPDF2==2.12.1
Requires-Dist: camelot-py[cv]>=0.10.0
Requires-Dist: opencv-python>=4.0.0
Requires-Dist: pdf2image>=1.16.0
Requires-Dist: pypdf>=3.0.0
Requires-Dist: filetype>=1.0.0
Requires-Dist: pdfplumber>=0.7.0
Requires-Dist: pdfminer.six>=20200726
Provides-Extra: dev
Requires-Dist: pytest>=6.0; extra == "dev"
Requires-Dist: flake8>=3.9; extra == "dev"
Requires-Dist: mypy>=0.800; extra == "dev"
